iopool/__init__.py
iopool/client.py
iopool/const.py
iopool/errors.py
iopool/meta.py
iopool/types.py
iopool-0.0.1.dist-info/WHEEL
iopool-0.0.1.dist-info/METADATA
iopool-0.0.1.dist-info/license_files/LICENSE
iopool-0.0.1.dist-info/RECORD
